look_edge_web
pyarmor_runtime_000000
