Metadata-Version: 2.4
Name: look_edge_web
Version: 0.3.8
Summary: a look edge web library , support both win and mac 
Author: dkflex
Author-email: 
Keywords: python,look edge web,look-edge-web,windows
Classifier: Development Status :: 1 - Planning
Classifier: Intended Audience :: Developers
Classifier: Programming Language :: Python :: 3
Classifier: Operating System :: Microsoft :: Windows
Requires-Dist: pywin32
Requires-Dist: psutil
Dynamic: author
Dynamic: classifier
Dynamic: description
Dynamic: description-content-type
Dynamic: keywords
Dynamic: requires-dist
Dynamic: summary
